topsis/102203979_main.py
topsis/__init__.py
topsis/main.py
topsis_arnav_102203979-1.5.dist-info/METADATA
topsis_arnav_102203979-1.5.dist-info/WHEEL
topsis_arnav_102203979-1.5.dist-info/entry_points.txt
topsis_arnav_102203979-1.5.dist-info/top_level.txt
topsis_arnav_102203979-1.5.dist-info/RECORD
