Metadata-Version: 2.1
Name: topsis_arnav_102203979
Version: 1.5
Summary: Python implementation of the TOPSIS method for multi-criteria decision analysis
Home-page: https://github.com/Arnavsmayan/Topsis
Requires-Dist: numpy
Requires-Dist: pandas
